bigquery_magics/__init__.py
bigquery_magics/_versions_helpers.py
bigquery_magics/bigquery.py
bigquery_magics/config.py
bigquery_magics/environment.py
bigquery_magics/graph_server.py
bigquery_magics/pyformat.py
bigquery_magics/version.py
bigquery_magics/line_arg_parser/__init__.py
bigquery_magics/line_arg_parser/exceptions.py
bigquery_magics/line_arg_parser/lexer.py
bigquery_magics/line_arg_parser/parser.py
bigquery_magics/line_arg_parser/visitors.py
bigquery_magics-0.11.0.dist-info/licenses/LICENSE
bigquery_magics-0.11.0.dist-info/METADATA
bigquery_magics-0.11.0.dist-info/WHEEL
bigquery_magics-0.11.0.dist-info/top_level.txt
bigquery_magics-0.11.0.dist-info/RECORD
