Metadata-Version: 2.4
Name: bigquery-magics
Version: 0.11.0
Summary: Google BigQuery magics for Jupyter and IPython
Home-page: https://github.com/googleapis/python-bigquery-magics
Author: Google LLC
Author-email: googleapis-packages@google.com
License: Apache 2.0
Platform: Posix; MacOS X; Windows
Classifier: Development Status :: 4 - Beta
Classifier: Intended Audience :: Developers
Classifier: License :: OSI Approved :: Apache Software License
Classifier: Programming Language :: Python
Classifier: Programming Language :: Python :: 3
Classifier: Programming Language :: Python :: 3.9
Classifier: Programming Language :: Python :: 3.10
Classifier: Programming Language :: Python :: 3.11
Classifier: Programming Language :: Python :: 3.12
Classifier: Programming Language :: Python :: 3.13
Classifier: Programming Language :: Python :: 3.14
Classifier: Operating System :: OS Independent
Classifier: Topic :: Internet
Requires-Python: >=3.9
License-File: LICENSE
Requires-Dist: db-dtypes<2.0.0,>=0.3.0
Requires-Dist: google-cloud-bigquery<4.0.0,>=3.13.0
Requires-Dist: ipywidgets>=7.7.1
Requires-Dist: ipython>=7.23.1
Requires-Dist: ipykernel>=5.5.6
Requires-Dist: packaging>=20.0.0
Requires-Dist: pandas>=1.2.0
Requires-Dist: pyarrow>=3.0.0
Requires-Dist: pydata-google-auth>=1.5.0
Requires-Dist: tqdm<5.0.0,>=4.7.4
Provides-Extra: bqstorage
Requires-Dist: google-cloud-bigquery-storage<3.0.0,>=2.6.0; extra == "bqstorage"
Requires-Dist: grpcio<2.0.0,>=1.47.0; extra == "bqstorage"
Requires-Dist: grpcio<2.0.0,>=1.49.1; (python_version >= "3.11" and python_version < "3.14") and extra == "bqstorage"
Requires-Dist: grpcio<2.0.0,>=1.75.1; python_version >= "3.14" and extra == "bqstorage"
Provides-Extra: bigframes
Requires-Dist: bigframes>=1.17.0; extra == "bigframes"
Provides-Extra: geopandas
Requires-Dist: geopandas>=1.0.1; extra == "geopandas"
Provides-Extra: spanner-graph-notebook
Requires-Dist: spanner-graph-notebook>=1.1.7; extra == "spanner-graph-notebook"
Requires-Dist: portpicker; extra == "spanner-graph-notebook"
Provides-Extra: all
Requires-Dist: google-cloud-bigquery-storage<3.0.0,>=2.6.0; extra == "all"
Requires-Dist: grpcio<2.0.0,>=1.47.0; extra == "all"
Requires-Dist: grpcio<2.0.0,>=1.49.1; (python_version >= "3.11" and python_version < "3.14") and extra == "all"
Requires-Dist: grpcio<2.0.0,>=1.75.1; python_version >= "3.14" and extra == "all"
Requires-Dist: bigframes>=1.17.0; extra == "all"
Requires-Dist: geopandas>=1.0.1; extra == "all"
Requires-Dist: spanner-graph-notebook>=1.1.7; extra == "all"
Requires-Dist: portpicker; extra == "all"
Dynamic: author
Dynamic: author-email
Dynamic: classifier
Dynamic: description
Dynamic: home-page
Dynamic: license
Dynamic: license-file
Dynamic: platform
Dynamic: provides-extra
Dynamic: requires-dist
Dynamic: requires-python
Dynamic: summary
